{
  "subagent": "integration-tester",
  "phase": "Phase 5 (Integration)",
  "story_id": "STORY-523",
  "timestamp": "2026-03-02T00:00:00Z",
  "integration_test_report": {
    "anti_gaming": "PASS",
    "test_summary": {
      "total": 77,
      "passed": 77,
      "failed": 0,
      "skipped": 0,
      "test_categories": {
        "ac1_section_existence": 60,
        "ac1_section_order": 12,
        "ac2_test_integrity_snapshot": 2,
        "ac3_session_memory_steps": 3
      }
    },
    "coverage": {
      "component_interactions": {
        "phase_file_structure": "100% (60/60 section checks)",
        "cross_file_consistency": "100% (12/12 files verified)",
        "mandatory_optional_markers": "100% (phase-02 markers validated)"
      },
      "integration_points": {
        "file_parsing": "VERIFIED - All 12 files parse correctly",
        "section_ordering": "VERIFIED - Consistent across all files",
        "documentation_completeness": "VERIFIED - No missing sections"
      },
      "scope": "Documentation-only change (no code coverage required)"
    },
    "performance": {
      "total_execution_time": "0.3s",
      "test_distribution": {
        "fastest_test": "0.01s",
        "slowest_test": "0.05s"
      }
    },
    "findings": {
      "critical": 0,
      "high": 0,
      "medium": 0,
      "low": 0,
      "total_issues": 0
    },
    "detailed_results": {
      "ac1_section_existence": {
        "status": "PASS",
        "description": "All 12 phase files contain all 5 required sections (Mandatory Steps, Validation Checkpoint, Pre-Exit Checklist, Optional Captures, Exit Gate)",
        "files_verified": 12,
        "section_checks": 60,
        "all_passed": true
      },
      "ac1_section_order": {
        "status": "PASS",
        "description": "Section ordering is correct in all 12 files: Mandatory < Validation < Pre-Exit < Optional < Exit",
        "files_verified": 12,
        "ordering_correct": true
      },
      "ac2_test_integrity_snapshot": {
        "status": "PASS",
        "description": "Phase 02 (test-first.md) contains test integrity snapshot under Mandatory Steps with [MANDATORY] marker",
        "markers_found": 1,
        "mandatory_marker_present": true
      },
      "ac3_session_memory_steps": {
        "status": "PASS",
        "description": "Phase 01 (preflight.md) contains all three session memory steps under Mandatory Steps: session memory, stale cleanup, context preservation",
        "steps_found": 3,
        "all_steps_present": true
      }
    },
    "cross_file_consistency": {
      "status": "VERIFIED",
      "summary": [
        "All 12 files use identical 5-section structure",
        "No duplicate section headers detected",
        "Section order enforced consistently across all phases",
        "Complete structural uniformity achieved"
      ],
      "files_checked": 12,
      "consistency_score": "100%"
    },
    "test_quality_metrics": {
      "assertions_per_test": "1-2 (focused assertions)",
      "assertion_specificity": "HIGH - grep patterns validate exact section headers",
      "mocking_ratio": "0 (no mocks required - documentation test)",
      "test_isolation": "COMPLETE - bash script tests against immutable markdown files",
      "aaa_pattern": "PROPER - Arrange (load files), Act (grep sections), Assert (check line order)"
    },
    "recommendations": [
      "Documentation structure is now standardized across all 12 phase files",
      "No code changes required - integration tests verify documentation-only changes",
      "All acceptance criteria successfully validated",
      "Ready for QA approval - documentation compliance verified"
    ]
  },
  "observations": [
    {
      "id": "OBS-001",
      "category": "documentation_compliance",
      "note": "All 12 phase files have been successfully restructured with consistent 5-section layout",
      "severity": "INFO"
    },
    {
      "id": "OBS-002",
      "category": "structural_consistency",
      "note": "Cross-file verification confirms no section header duplicates or ordering violations",
      "severity": "INFO"
    },
    {
      "id": "OBS-003",
      "category": "test_quality",
      "note": "Integration test uses proper AAA pattern with focused assertions (grep exact headers, validate order via line numbers)",
      "severity": "INFO"
    }
  ],
  "metadata": {
    "story_type": "DOCUMENTATION",
    "phase_count": 12,
    "test_type": "INTEGRATION",
    "test_framework": "bash/grep",
    "validation_complete": true,
    "ready_for_qa": true
  }
}
